acerim/__init__.py
acerim/aceclasses.py
acerim/acefunctions.py
acerim/acestats.py
acerim/version.py
acerim/sample/__init__.py
acerim/sample/craters.csv
acerim/sample/moon.tif
acerim/sample/tutorial.py
acerim/tests/__init__.py
acerim/tests/test_classes.py
acerim/tests/test_functions.py
acerim-0.1.dist-info/DESCRIPTION.rst
acerim-0.1.dist-info/METADATA
acerim-0.1.dist-info/RECORD
acerim-0.1.dist-info/WHEEL
acerim-0.1.dist-info/metadata.json
acerim-0.1.dist-info/top_level.txt
