Metadata-Version: 2.0
Name: acerim
Version: 0.1
Summary: A package for analyzing impact crater ejecta.
Home-page: http://github.com/cjtu/acerim
Author: Christian Tai Udovicic
Author-email: cj.taiudovicic@gmail.com
License: MIT
Keywords: planetary science crater ejecta data analysis
Platform: OS Independent
Classifier: Development Status :: 3 - Alpha
Classifier: Intended Audience :: Science/Research
Classifier: License :: OSI Approved :: MIT License
Classifier: Natural Language :: English
Classifier: Operating System :: OS Independent
Classifier: Topic :: Scientific/Engineering :: Astronomy
Classifier: Programming Language :: Python :: 2
Classifier: Programming Language :: Python :: 2.7
Classifier: Programming Language :: Python :: 3
Classifier: Programming Language :: Python :: 3.2
Classifier: Programming Language :: Python :: 3.3
Requires-Dist: gdal
Requires-Dist: matplotlib
Requires-Dist: numpy
Requires-Dist: pandas
Requires-Dist: scipy
